KnnImp7.py
KnnImp7-1.0.1.dist-info/METADATA
KnnImp7-1.0.1.dist-info/RECORD
KnnImp7-1.0.1.dist-info/WHEEL
KnnImp7-1.0.1.dist-info/top_level.txt
