Metadata-Version: 2.1
Name: KnnImp7
Version: 1.0.1
Summary: LOL
Home-page: UNKNOWN
Author: gop
Author-email: hello.korea.6174@gmail.com
License: MIT
Platform: UNKNOWN
Requires-Python: >=3
